lgm/__init__.py
lgm/agents.py
lgm/awd_lstm.py
lgm/callbacks.py
lgm/data_block.py
lgm/datasets.py
lgm/environments.py
lgm/hooks.py
lgm/learner.py
lgm/metrics.py
lgm/optimizer.py
lgm/rlearner.py
lgm/utils.py
lgm-0.1.0.dist-info/LICENSE
lgm-0.1.0.dist-info/METADATA
lgm-0.1.0.dist-info/WHEEL
lgm-0.1.0.dist-info/top_level.txt
lgm-0.1.0.dist-info/RECORD
