Metadata-Version: 2.1
Name: lgm
Version: 0.1.0
Summary: Lightweight python3 library for natural LanGuage Modeling (LGM), useful for deep learning and reinforcement learning experiments with natural language data.
Home-page: https://github.com/abrsvn/lgm
Author: Adrian Brasoveanu
Author-email: abrsvn@gmail.com
License: GNU General Public License v3.0
Platform: UNKNOWN
